swarmauri_middleware_cachecontrol/CacheControlMiddleware.py
swarmauri_middleware_cachecontrol/__init__.py
swarmauri_middleware_cachecontrol-0.8.0.dev5.dist-info/LICENSE
swarmauri_middleware_cachecontrol-0.8.0.dev5.dist-info/METADATA
swarmauri_middleware_cachecontrol-0.8.0.dev5.dist-info/WHEEL
swarmauri_middleware_cachecontrol-0.8.0.dev5.dist-info/entry_points.txt
swarmauri_middleware_cachecontrol-0.8.0.dev5.dist-info/RECORD
