Metadata-Version: 2.3
Name: swarmauri_middleware_cachecontrol
Version: 0.8.0.dev5
Summary: Middleware for managing HTTP cache headers and client-side caching behavior.
License: Apache-2.0
Author: Jacob Stewart
Author-email: jacob@swarmauri.com
Requires-Python: >=3.10,<3.13
Classifier: License :: OSI Approved :: Apache Software License
Classifier: Natural Language :: English
Classifier: Programming Language :: Python :: 3.10
Classifier: Programming Language :: Python :: 3.11
Classifier: Programming Language :: Python :: 3.12
Classifier: Programming Language :: Python :: 3.13
Classifier: Development Status :: 3 - Alpha
Classifier: Typing :: Typed
Requires-Dist: fastapi
Requires-Dist: python-dotenv (>=0.19.0)
Requires-Dist: swarmauri_base
Requires-Dist: swarmauri_core
Requires-Dist: swarmauri_standard
